chaudio/__init__.py
chaudio/track.py
chaudio/arrangers/__init__.py
chaudio/instruments/__init__.py
chaudio/io/__init__.py
chaudio/plugins/__init__.py
chaudio/plugins/echo.py
chaudio/plugins/fade.py
chaudio/plugins/filters.py
chaudio/plugins/noise.py
chaudio/plugins/resolution.py
chaudio/plugins/volume.py
chaudio/samples/bass.wav
chaudio/samples/hat_closed.wav
chaudio/samples/hat_opened.wav
chaudio/samples/snare.wav
chaudio/source/__init__.py
chaudio/tests/__init__.py
chaudio/tests/test_waveforms.py
chaudio/util/__init__.py
chaudio/waves/__init__.py
chaudio-0.0.8.data/data/chaudio/samples/bass.wav
chaudio-0.0.8.data/data/chaudio/samples/hat_closed.wav
chaudio-0.0.8.data/data/chaudio/samples/hat_opened.wav
chaudio-0.0.8.data/data/chaudio/samples/snare.wav
chaudio-0.0.8.data/data/examples/addnoise.py
chaudio-0.0.8.data/data/examples/arrange.py
chaudio-0.0.8.data/data/examples/simple.py
chaudio-0.0.8.dist-info/DESCRIPTION.rst
chaudio-0.0.8.dist-info/METADATA
chaudio-0.0.8.dist-info/RECORD
chaudio-0.0.8.dist-info/WHEEL
chaudio-0.0.8.dist-info/metadata.json
chaudio-0.0.8.dist-info/top_level.txt
