Metadata-Version: 2.0
Name: chaudio
Version: 0.0.8
Summary: Programmatic music synthesis
Home-page: https://github.com/chemicaldevelopment/chaudio
Author: Cade Brown
Author-email: cade@chemicaldevelopment.us
License: GPLv3
Keywords: audio music synthesis processing
Platform: UNKNOWN
Classifier: Topic :: Multimedia :: Sound/Audio :: Sound Synthesis
Requires-Dist: numpy
Requires-Dist: scipy
Requires-Dist: simpleaudio
Provides-Extra: test
Requires-Dist: coverage; extra == 'test'
